slack_types/__init__.py
slack_types/app_backend/__init__.py
slack_types/app_backend/dialogs/__init__.py
slack_types/app_backend/dialogs/dialog_cancellation_payload.py
slack_types/app_backend/dialogs/dialog_submission_payload.py
slack_types/app_backend/dialogs/dialog_suggestion_payload.py
slack_types/app_backend/interactive_components/__init__.py
slack_types/app_backend/interactive_components/attachment_action_payload.py
slack_types/app_backend/interactive_components/block_action_payload.py
slack_types/app_backend/interactive_components/message_shortcut_payload.py
slack_types/app_backend/slash_commands/__init__.py
slack_types/app_backend/slash_commands/slash_command_payload.py
slack_types/app_backend/views/__init__.py
slack_types/app_backend/views/view_closed_payload.py
slack_types/app_backend/views/view_submission_payload.py
slack_types/audit_api/__init__.py
slack_types/audit_api/v1/__init__.py
slack_types/audit_api/v1/actions_response.py
slack_types/audit_api/v1/logs_response.py
slack_types/audit_api/v1/schemas_response.py
slack_types/events_api/__init__.py
slack_types/events_api/app_home_opened_payload.py
slack_types/events_api/app_mention_payload.py
slack_types/events_api/app_rate_limited_payload.py
slack_types/events_api/app_requested_payload.py
slack_types/events_api/app_uninstalled_payload.py
slack_types/events_api/call_rejected_payload.py
slack_types/events_api/channel_archive_payload.py
slack_types/events_api/channel_created_payload.py
slack_types/events_api/channel_deleted_payload.py
slack_types/events_api/channel_history_changed_payload.py
slack_types/events_api/channel_id_changed_payload.py
slack_types/events_api/channel_left_payload.py
slack_types/events_api/channel_rename_payload.py
slack_types/events_api/channel_shared_payload.py
slack_types/events_api/channel_unarchive_payload.py
slack_types/events_api/channel_unshared_payload.py
slack_types/events_api/dnd_updated_payload.py
slack_types/events_api/dnd_updated_user_payload.py
slack_types-0.0.2.dist-info/LICENSE.txt
slack_types-0.0.2.dist-info/METADATA
slack_types-0.0.2.dist-info/WHEEL
slack_types-0.0.2.dist-info/top_level.txt
slack_types-0.0.2.dist-info/RECORD
