Metadata-Version: 2.1
Name: slack-types
Version: 0.0.2
Summary: Slack API Types in Python
Home-page: https://github.com/warrenseine/slack-types
Author: Warren Seine @warrenseine
Author-email: warren.seine@gmail.com
License: UNKNOWN
Project-URL: Bug Tracker, https://github.com/warrenseine/slack-types/issues
Platform: UNKNOWN
Classifier: Programming Language :: Python :: 3
Classifier: License :: OSI Approved :: MIT License
Classifier: Operating System :: OS Independent
Requires-Python: >=3.7
License-File: LICENSE.txt
